thingdl/__init__.py
thingdl/thingiverse_downloader.py
thingdl-1.1.0.dist-info/LICENSE
thingdl-1.1.0.dist-info/METADATA
thingdl-1.1.0.dist-info/WHEEL
thingdl-1.1.0.dist-info/entry_points.txt
thingdl-1.1.0.dist-info/top_level.txt
thingdl-1.1.0.dist-info/RECORD
