Metadata-Version: 2.1
Name: thingdl
Version: 1.1.0
Summary: This provides a utility to bulk download files from a thing in Thingiverse
Home-page: https://github.com/sean-bailey
Author: Sean Bailey
Author-email: seanbailey518@gmail.com
License: UNKNOWN
Platform: UNKNOWN
Classifier: Programming Language :: Python :: 3
Classifier: License :: OSI Approved :: GNU Affero General Public License v3 or later (AGPLv3+)
Classifier: Operating System :: OS Independent
Requires-Python: >=3.6
License-File: LICENSE
Requires-Dist: requests (>=2.27.1)
Requires-Dist: fake-useragent (>=0.1.11)
Requires-Dist: webdriver-selector (>=1.0.2)
Requires-Dist: beautifulsoup4 (>=4.10.0)
